python_analytics_accelerator/__init__.py
python_analytics_accelerator/catalog.py
python_analytics_accelerator/cli.py
python_analytics_accelerator/config.py
python_analytics_accelerator/metrics.py
python_analytics_accelerator/plots.py
python_analytics_accelerator/utils.py
python_analytics_accelerator/etl/extract.py
python_analytics_accelerator/etl/run.py
python_analytics_accelerator/etl/transform.py
python_analytics_accelerator/ingest/__init__.py
python_analytics_accelerator/ingest/graphql_queries.py
python_analytics_accelerator-0.3.0.dist-info/METADATA
python_analytics_accelerator-0.3.0.dist-info/WHEEL
python_analytics_accelerator-0.3.0.dist-info/entry_points.txt
python_analytics_accelerator-0.3.0.dist-info/RECORD
